pgmenus/__init__.py
pgmenus-0.0.38.dist-info/METADATA
pgmenus-0.0.38.dist-info/WHEEL
pgmenus-0.0.38.dist-info/licenses/LICENSE
pgmenus-0.0.38.dist-info/RECORD
